paddle/__init__.py
paddle/auth.py
paddle/client.py
paddle/exceptions.py
paddle/operations/__init__.py
paddle/operations/addresses.py
paddle/operations/businesses.py
paddle/operations/customers.py
paddle/operations/payment_methods.py
paddle/operations/subscriptions.py
paddle/operations/transactions.py
paddle/schemas/__init__.py
paddle/schemas/address.py
paddle/schemas/adjustment.py
paddle/schemas/api_key.py
paddle/schemas/business.py
paddle/schemas/customer.py
paddle/schemas/discount.py
paddle/schemas/payment_method.py
paddle/schemas/payout.py
paddle/schemas/price.py
paddle/schemas/product.py
paddle/schemas/report.py
paddle/schemas/subscription.py
paddle/schemas/transaction.py
paddle/schemas/human/__init__.py
paddle/schemas/human/response.py
paddle/webhooks/__init__.py
paddle/webhooks/exceptions.py
paddle/webhooks/verifier.py
python_paddle-0.3.6.dist-info/licenses/LICENSE
python_paddle-0.3.6.dist-info/METADATA
python_paddle-0.3.6.dist-info/WHEEL
python_paddle-0.3.6.dist-info/top_level.txt
python_paddle-0.3.6.dist-info/RECORD
