Metadata-Version: 2.4
Name: python-paddle
Version: 0.3.6
Summary: An unofficial SDK for Paddle's billing API and webhooks.
Author: Nyeki
License: Business Source License 1.0
Requires-Python: >=3.13
License-File: LICENSE
Requires-Dist: httpx>=0.28.1
Requires-Dist: pydantic>=2.12.5
Dynamic: license-file
